{"IcoMoonType":"selection","icons":[{"icon":{"paths":["M512 854q140 0 241-101t101-241-101-241-241-101-241 101-101 241 101 241 241 101zM512 86q176 0 301 125t125 301-125 301-301 125-301-125-125-301 125-301 301-125zM470 298h84v256h-84v-256zM470 640h84v86h-84v-86z"],"attrs":[],"isMulticolor":false,"isMulticolor2":false,"tags":["error_outline"],"grid":24},"attrs":[],"properties":{"order":112,"ligatures":"error","id":1,"name":"error","prevSize":24,"code":59655},"setIdx":3,"setId":1,"iconIdx":1},{"icon":{"paths":["M384 214h426v426h-84v-282l-496 496-60-60 496-496h-282v-84z"],"attrs":[],"isMulticolor":false,"isMulticolor2":false,"tags":["call_made"],"grid":24},"attrs":[],"properties":{"order":113,"ligatures":"upright","id":90,"name":"upright","prevSize":24,"code":59661},"setIdx":3,"setId":1,"iconIdx":90},{"icon":{"paths":["M512 490q44 0 75-31t31-75-31-75-75-31-75 31-31 75 31 75 75 31zM512 86q124 0 211 87t87 211q0 62-31 142t-75 150-87 131-73 97l-32 34q-12-14-32-37t-72-92-91-134-71-147-32-144q0-124 87-211t211-87z"],"attrs":[],"isMulticolor":false,"isMulticolor2":false,"tags":["location_on","place","room"],"grid":24},"attrs":[],"properties":{"order":107,"ligatures":"place","id":107,"name":"place","prevSize":24,"code":59648},"setIdx":3,"setId":1,"iconIdx":107},{"icon":{"paths":["M810 554h-256v256h-84v-256h-256v-84h256v-256h84v256h256v84z"],"attrs":[],"isMulticolor":false,"isMulticolor2":false,"tags":["add"],"grid":24},"attrs":[],"properties":{"order":114,"ligatures":"add","id":146,"prevSize":24,"code":59662,"name":"add"},"setIdx":3,"setId":1,"iconIdx":146},{"icon":{"paths":["M810 274l-238 238 238 238-60 60-238-238-238 238-60-60 238-238-238-238 60-60 238 238 238-238z"],"attrs":[],"isMulticolor":false,"isMulticolor2":false,"tags":["clear, close"],"grid":24},"attrs":[],"properties":{"order":110,"ligatures":"clear, close","id":153,"prevSize":24,"code":59658,"name":"close"},"setIdx":3,"setId":1,"iconIdx":153},{"icon":{"paths":["M726 298q88 0 150 63t62 151-62 151-150 63h-172v-82h172q54 0 93-39t39-93-39-93-93-39h-172v-82h172zM342 554v-84h340v84h-340zM166 512q0 54 39 93t93 39h172v82h-172q-88 0-150-63t-62-151 62-151 150-63h172v82h-172q-54 0-93 39t-39 93z"],"attrs":[],"isMulticolor":false,"isMulticolor2":false,"tags":["link, insert_link"],"grid":24},"attrs":[],"properties":{"order":115,"ligatures":"link","id":164,"prevSize":24,"code":59663,"name":"link"},"setIdx":3,"setId":1,"iconIdx":164},{"icon":{"paths":["M726 554v-84h-428v84h428zM512 86q176 0 301 125t125 301-125 301-301 125-301-125-125-301 125-301 301-125z"],"attrs":[],"isMulticolor":false,"isMulticolor2":false,"tags":["remove_circle","do_not_disturb_on"],"grid":24},"attrs":[],"properties":{"order":102,"ligatures":"remove","id":167,"name":"remove","prevSize":24,"code":59649},"setIdx":3,"setId":1,"iconIdx":167},{"icon":{"paths":["M316 366l196 196 196-196 60 60-256 256-256-256z"],"attrs":[],"isMulticolor":false,"isMulticolor2":false,"tags":["keyboard_arrow_down"],"grid":24},"attrs":[],"properties":{"order":97,"ligatures":"down","id":342,"name":"down","prevSize":24,"code":59650},"setIdx":3,"setId":1,"iconIdx":342},{"icon":{"paths":["M658 708l-60 60-256-256 256-256 60 60-196 196z"],"attrs":[],"isMulticolor":false,"isMulticolor2":false,"tags":["keyboard_arrow_left"],"grid":24},"attrs":[],"properties":{"order":98,"ligatures":"left","id":343,"name":"left","prevSize":24,"code":59651},"setIdx":3,"setId":1,"iconIdx":343},{"icon":{"paths":["M366 708l196-196-196-196 60-60 256 256-256 256z"],"attrs":[],"isMulticolor":false,"isMulticolor2":false,"tags":["keyboard_arrow_right"],"grid":24},"attrs":[],"properties":{"order":99,"ligatures":"right","id":344,"name":"right","prevSize":24,"code":59652},"setIdx":3,"setId":1,"iconIdx":344},{"icon":{"paths":["M316 658l-60-60 256-256 256 256-60 60-196-196z"],"attrs":[],"isMulticolor":false,"isMulticolor2":false,"tags":["keyboard_arrow_up"],"grid":24},"attrs":[],"properties":{"order":100,"ligatures":"up","id":345,"name":"up","prevSize":24,"code":59653},"setIdx":3,"setId":1,"iconIdx":345},{"icon":{"paths":["M128 256h768v86h-768v-86zM128 554v-84h768v84h-768zM128 768v-86h768v86h-768z"],"attrs":[],"isMulticolor":false,"isMulticolor2":false,"tags":["menu"],"grid":24},"attrs":[],"properties":{"order":108,"ligatures":"menu","id":600,"prevSize":24,"code":59659,"name":"menu"},"setIdx":3,"setId":1,"iconIdx":600},{"icon":{"paths":["M512 598q108 0 225 47t117 123v86h-684v-86q0-76 117-123t225-47zM512 512q-70 0-120-50t-50-120 50-121 120-51 120 51 50 121-50 120-120 50z"],"attrs":[],"isMulticolor":false,"isMulticolor2":false,"tags":["person"],"grid":24},"attrs":[],"properties":{"order":101,"ligatures":"user","id":685,"prevSize":24,"code":59654,"name":"user"},"setIdx":3,"setId":1,"iconIdx":685},{"icon":{"paths":["M554 384v-86h-84v86h84zM554 726v-256h-84v256h84zM512 86q176 0 301 125t125 301-125 301-301 125-301-125-125-301 125-301 301-125z"],"attrs":[],"isMulticolor":false,"isMulticolor2":false,"tags":["info"],"grid":24},"attrs":[],"properties":{"order":109,"ligatures":"info","id":760,"prevSize":24,"code":59660,"name":"info"},"setIdx":3,"setId":1,"iconIdx":760},{"icon":{"paths":["M406 598q80 0 136-56t56-136-56-136-136-56-136 56-56 136 56 136 136 56zM662 598l212 212-64 64-212-212v-34l-12-12q-76 66-180 66-116 0-197-80t-81-196 81-197 197-81 196 81 80 197q0 42-20 95t-46 85l12 12h34z"],"attrs":[],"isMulticolor":false,"isMulticolor2":false,"tags":["search"],"grid":24},"attrs":[],"properties":{"order":106,"ligatures":"search","id":789,"prevSize":24,"code":59656,"name":"search"},"setIdx":3,"setId":1,"iconIdx":789},{"icon":{"paths":["M662 170h148v86h-596v-86h148l44-42h212zM342 384v426h340v-426h-340zM256 810v-512h512v512q0 34-26 60t-60 26h-340q-34 0-60-26t-26-60z"],"attrs":[],"isMulticolor":false,"isMulticolor2":false,"tags":["delete_outline"],"grid":24},"attrs":[],"properties":{"order":104,"ligatures":"trash","id":896,"prevSize":24,"code":59657,"name":"trash"},"setIdx":3,"setId":1,"iconIdx":896}],"height":1024,"metadata":{"name":"dmart"},"preferences":{"showGlyphs":true,"showCodes":true,"showQuickUse":true,"showQuickUse2":true,"showSVGs":true,"fontPref":{"prefix":"icon-","metadata":{"fontFamily":"dmart","majorVersion":1,"minorVersion":0},"metrics":{"emSize":1024,"baseline":6.25,"whitespace":50},"embed":false,"noie8":true,"ie7":false,"cssVars":true,"cssVarsFormat":"less","showSelector":true,"showVersion":true},"imagePref":{"prefix":"icon-","png":true,"useClassSelector":true,"color":0,"bgColor":16777215,"name":"icomoon","classSelector":".icon"},"historySize":50,"gridSize":16,"showGrid":true,"showLiga":true}}